mongomock_motor/__init__.py
mongomock_motor/patches.py
mongomock_motor-0.0.33.dist-info/LICENSE
mongomock_motor-0.0.33.dist-info/METADATA
mongomock_motor-0.0.33.dist-info/WHEEL
mongomock_motor-0.0.33.dist-info/RECORD
