Metadata-Version: 2.1
Name: mongomock-motor
Version: 0.0.33
Summary: Library for mocking AsyncIOMotorClient built on top of mongomock.
Home-page: https://github.com/michaelkryukov/mongomock_motor
License: MIT
Keywords: library,mongodb
Author: Michael Kryukov
Author-email: mkrukov@bestplace.pro
Requires-Python: >=3.8,<4.0
Classifier: License :: OSI Approved :: MIT License
Classifier: Programming Language :: Python :: 3
Classifier: Programming Language :: Python :: 3.8
Classifier: Programming Language :: Python :: 3.9
Classifier: Programming Language :: Python :: 3.10
Classifier: Programming Language :: Python :: 3.11
Classifier: Programming Language :: Python :: 3.12
Requires-Dist: mongomock (>=4.1.2,<5.0.0)
Project-URL: Repository, https://github.com/michaelkryukov/mongomock_motor
